requests_extra/__init__.py
requests_extra/api.py
requests_extra/defaults.py
requests_extra/sessions.py
requests_extra/internal/__init__.py
requests_extra/internal/cache.py
requests_extra/internal/session_cache.py
requests_extra/internal/utils.py
requests_extra-1.0.0b8.dist-info/LICENSE
requests_extra-1.0.0b8.dist-info/METADATA
requests_extra-1.0.0b8.dist-info/WHEEL
requests_extra-1.0.0b8.dist-info/top_level.txt
requests_extra-1.0.0b8.dist-info/RECORD
