Metadata-Version: 2.1
Name: requests-extra
Version: 1.0.0b8
Summary: Drop-in wrapper around the Python Requests library that provides extra features.
Home-page: https://github.com/requests-extra/requests-extra
Author: requests-extra contributors and the upstream projects authors
Author-email: UNKNOWN
License: UNKNOWN
Keywords: requests,timeout,retry,exception,brotli
Platform: UNKNOWN
Classifier: Programming Language :: Python :: 3.6
Classifier: Programming Language :: Python :: 3.7
Classifier: Programming Language :: Python :: 3.8
Classifier: Development Status :: 4 - Beta
Classifier: Intended Audience :: Developers
Classifier: License :: OSI Approved :: Apache Software License
Classifier: Operating System :: OS Independent
Classifier: Topic :: Internet :: WWW/HTTP
Requires-Dist: requests (<3,>=2.25.1)
Requires-Dist: urllib3 (<2,>=1.26)
Requires-Dist: brotli
